Workbook

Sheet Cover
B2: CarbonOS
B3: Platform Financial Model — Investor Summary
B5: Prepared by Ashik Karim
B6: Confidential — June 2026
B9: Contents:
B10: 1. Assumptions — all editable drivers (blue = inputs)
B11: 2. Market — TAM / SAM / SOM
B12: 3. Revenue Build — six monetization streams
B13: 4. P&L — 7-year projection
B14: 5. Unit Economics — SaaS metrics
B15: 6. Valuation — comps-based enterprise value
B16: 7. Scenarios — bear / base / bull penetration
... B23: forecast of actual results. Market data sourced on the Sources tab.

Sheet Assumptions
A1: Assumptions
A2: All blue cells are editable inputs. Black = calculated.
A4: ($ in millions unless noted) | C4: 2026 | D4: 2027 | E4: 2028 | F4: 2029 | G4: 2030 | H4: 2031 | I4: 2032
A6: MARKET DRIVERS
A7: Addressable carbon throughput (Mt CO2e) | C7: 350 | D7: 500 | E7: 680 | F7: 860 | G7: 1010 | H7: 1150 | I7: 1300
A8: Blended credit price ($/tCO2e) | C8: 18 | D8: 20 | E8: 23 | F8: 26 | G8: 28 | H8: 30 | I8: 32
A9: Global credit issuance value ($mm) | C9: =C7*C8 -> 6300 | D9: =D7*D8 -> 10000 | E9: =E7*E8 -> 15640 | F9: =F7*F8 -> 22360 | G9: =G7*G8 -> 28280 | H9: =H7*H8 -> 34500 | I9: =I7*I8 -> 41600
A10: Secondary turnover multiple (x) | C10: 3 | D10: =$C$10 -> 3 | E10: =$C$10 -> 3 | F10: =$C$10 -> 3 | G10: =$C$10 -> 3 | H10: =$C$10 -> 3 | I10: =$C$10 -> 3
A11: Global secondary GMV ($mm) | C11: =C9*C10 -> 18900 | D11: =D9*D10 -> 30000 | E11: =E9*E10 -> 46920 | F11: =F9*F10 -> 67080 | G11: =G9*G10 -> 84840 | H11: =H9*H10 -> 103500 | I11: =I9*I10 -> 124800
A13: PLATFORM DRIVERS
A14: Platform penetration (% of throughput) | C14: 0.001 | D14: 0.004 | E14: 0.01 | F14: 0.02 | G14: 0.03 | H14: 0.04 | I14: 0.05
A15: Platform credits originated (Mt) | C15: =C7*C14 -> 0.35 | D15: =D7*D14 -> 2 | E15: =E7*E14 -> 6.8 | F15: =F7*F14 -> 17.2 | G15: =G7*G14 -> 30.3 | H15: =H7*H14 -> 46 | I15: =I7*I14 -> 65
A16: Platform issuance value ($mm) | C16: =C15*C8 -> 6.3 | D16: =D15*D8 -> 40 | E16: =E15*E8 -> 156.4 | F16: =F15*F8 -> 447.2 | G16: =G15*G8 -> 848.4 | H16: =H15*H8 -> 1380 | I16: =I15*I8 -> 2080
A17: Platform exchange turns (x) | C17: 2.5 | D17: =$C$17 -> 2.5 | E17: =$C$17 -> 2.5 | F17: =$C$17 -> 2.5 | G17: =$C$17 -> 2.5 | H17: =$C$17 -> 2.5 | I17: =$C$17 -> 2.5
A18: Platform exchange GMV ($mm) | C18: =C16*C17 -> 15.75 | D18: =D16*D17 -> 100 | E18: =E16*E17 -> 391 | F18: =F16*F17 -> 1118 | G18: =G16*G17 -> 2121 | H18: =H16*H17 -> 3450 | I18: =I16*I17 -> 5200
A19: Active developer projects (#) | C19: 40 | D19: 150 | E19: 400 | F19: 800 | G19: 1400 | H19: 2200 | I19: 3200
A20: Enterprise data seats (#) | C20: 50 | D20: 250 | E20: 600 | F20: 1100 | G20: 1700 | H20: 2200 | I20: 2500
A21: Capital arranged ($mm) | C21: 20 | D21: 80 | E21: 200 | F21: 500 | G21: 900 | H21: 1300 | I21: 1600
A23: RATE / PRICING CONSTANTS
A24: SaaS ARPU per project ($/yr) | C24: 45000 | D24: Procore/Carta-style blended seat+project
A25: Issuance success fee (% of issuance value) | C25: 0.02 | D25: vs broker/placement 2-5%
A26: Exchange take rate (% of GMV) | C26: 0.03 | D26: vs broker 10-20%; ServiceTitan pmts 1.17%
A27: Financing facilitation fee (% of capital) | C27: 0.025 | D27: vs IB placement 1-3%
A28: Data seat ARPU ($/yr) | C28: 22000 | D28: vs Bloomberg ~$30k; MSCI data
A29: Credit carry (% of issuance value) | C29: 0.005 | D29: conservative carried participation
A31: COST DRIVERS
A32: Headcount (#) | C32: 35 | D32: 90 | E32: 180 | F32: 320 | G32: 460 | H32: 560 | I32: 650
A33: Loaded cost / employee ($000) | C33: 165 | D33: fully-loaded incl. benefits
A34: Marketing & programs ($mm) | C34: 3 | D34: 10 | E34: 22 | F34: 38 | G34: 52 | H34: 62 | I34: 70
A35: Other G&A non-personnel ($mm) | C35: 2 | D35: 5 | E35: 10 | F35: 18 | G35: 26 | H35: 34 | I35: 40
A36: COGS (% of revenue) | C36: 0.48 | D36: 0.42 | E36: 0.36 | F36: 0.3 | G36: 0.26 | H36: 0.24 | I36: 0.22

Sheet Revenue Build
A1: Revenue Build
A2: Six monetization streams. Links (green) pull from Assumptions.
A4: ($ in millions unless noted) | C4: 2026 | D4: 2027 | E4: 2028 | F4: 2029 | G4: 2030 | H4: 2031 | I4: 2032
A6: 1. Developer platform SaaS | C6: =Assumptions!C19*Assumptions!$C$24/1000000 -> 1.8 | D6: =Assumptions!D19*Assumptions!$C$24/1000000 -> 6.75 | E6: =Assumptions!E19*Assumptions!$C$24/1000000 -> 18 | F6: =Assumptions!F19*Assumptions!$C$24/1000000 -> 36 | G6: =Assumptions!G19*Assumptions!$C$24/1000000 -> 63 | H6: =Assumptions!H19*Assumptions!$C$24/1000000 -> 99 | I6: =Assumptions!I19*Assumptions!$C$24/1000000 -> 144
A7: 2. Issuance / success fee | C7: =Assumptions!C16*Assumptions!$C$25 -> 0.126 | D7: =Assumptions!D16*Assumptions!$C$25 -> 0.8 | E7: =Assumptions!E16*Assumptions!$C$25 -> 3.128 | F7: =Assumptions!F16*Assumptions!$C$25 -> 8.944 | G7: =Assumptions!G16*Assumptions!$C$25 -> 16.968 | H7: =Assumptions!H16*Assumptions!$C$25 -> 27.6 | I7: =Assumptions!I16*Assumptions!$C$25 -> 41.6
A8: 3. Marketplace / exchange take | C8: =Assumptions!C18*Assumptions!$C$26 -> 0.4725 | D8: =Assumptions!D18*Assumptions!$C$26 -> 3 | E8: =Assumptions!E18*Assumptions!$C$26 -> 11.73 | F8: =Assumptions!F18*Assumptions!$C$26 -> 33.54 | G8: =Assumptions!G18*Assumptions!$C$26 -> 63.63 | H8: =Assumptions!H18*Assumptions!$C$26 -> 103.5 | I8: =Assumptions!I18*Assumptions!$C$26 -> 156
A9: 4. Financing facilitation fee | C9: =Assumptions!C21*Assumptions!$C$27 -> 0.5 | D9: =Assumptions!D21*Assumptions!$C$27 -> 2 | E9: =Assumptions!E21*Assumptions!$C$27 -> 5 | F9: =Assumptions!F21*Assumptions!$C$27 -> 12.5 | G9: =Assumptions!G21*Assumptions!$C$27 -> 22.5 | H9: =Assumptions!H21*Assumptions!$C$27 -> 32.5 | I9: =Assumptions!I21*Assumptions!$C$27 -> 40
A10: 5. Data & intelligence subscriptions | C10: =Assumptions!C20*Assumptions!$C$28/1000000 -> 1.1 | D10: =Assumptions!D20*Assumptions!$C$28/1000000 -> 5.5 | E10: =Assumptions!E20*Assumptions!$C$28/1000000 -> 13.2 | F10: =Assumptions!F20*Assumptions!$C$28/1000000 -> 24.2 | G10: =Assumptions!G20*Assumptions!$C$28/1000000 -> 37.4 | H10: =Assumptions!H20*Assumptions!$C$28/1000000 -> 48.4 | I10: =Assumptions!I20*Assumptions!$C$28/1000000 -> 55
A11: 6. Credit carry / participation | C11: =Assumptions!C16*Assumptions!$C$29 -> 0.0315 | D11: =Assumptions!D16*Assumptions!$C$29 -> 0.2 | E11: =Assumptions!E16*Assumptions!$C$29 -> 0.782 | F11: =Assumptions!F16*Assumptions!$C$29 -> 2.236 | G11: =Assumptions!G16*Assumptions!$C$29 -> 4.242 | H11: =Assumptions!H16*Assumptions!$C$29 -> 6.9 | I11: =Assumptions!I16*Assumptions!$C$29 -> 10.4
A12: Total revenue | C12: =SUM(C6:C11) -> 4.03 | D12: =SUM(D6:D11) -> 18.25 | E12: =SUM(E6:E11) -> 51.84 | F12: =SUM(F6:F11) -> 117.42 | G12: =SUM(G6:G11) -> 207.74 | H12: =SUM(H6:H11) -> 317.9 | I12: =SUM(I6:I11) -> 447
A14: YoY growth | C14: - | D14: =IFERROR(D12/C12-1,"-") -> 3.528536 | E14: =IFERROR(E12/D12-1,"-") -> 1.8405479 | F14: =IFERROR(F12/E12-1,"-") -> 1.2650463 | G14: =IFERROR(G12/F12-1,"-") -> 0.76920456 | H14: =IFERROR(H12/G12-1,"-") -> 0.53027823 | I14: =IFERROR(I12/H12-1,"-") -> 0.40610255
A16: Revenue mix (% of total)
A17: SaaS | C17: =C6/C12 -> 0.44665012 | D17: =D6/D12 -> 0.36986301 | E17: =E6/E12 -> 0.34722222 | F17: =F6/F12 -> 0.30659172 | G17: =G6/G12 -> 0.3032637 | H17: =H6/H12 -> 0.31141869 | I17: =I6/I12 -> 0.32214765
A18: Issuance fee | C18: =C7/C12 -> 0.031265509 | D18: =D7/D12 -> 0.043835616 | E18: =E7/E12 -> 0.060339506 | F18: =F7/F12 -> 0.07617101 | G18: =G7/G12 -> 0.081679022 | H18: =H7/H12 -> 0.086819755 | I18: =I7/I12 -> 0.093064877
A19: Exchange | C19: =C8/C12 -> 0.11724566 | D19: =D8/D12 -> 0.16438356 | E19: =E8/E12 -> 0.22627315 | F19: =F8/F12 -> 0.28564129 | G19: =G8/G12 -> 0.30629633 | H19: =H8/H12 -> 0.32557408 | I19: =I8/I12 -> 0.34899329
A20: Financing | C20: =C9/C12 -> 0.12406948 | D20: =D9/D12 -> 0.10958904 | E20: =E9/E12 -> 0.096450617 | F20: =F9/F12 -> 0.10645546 | G20: =G9/G12 -> 0.10830846 | H20: =H9/H12 -> 0.10223341 | I20: =I9/I12 -> 0.089485459
A21: Data | C21: =C10/C12 -> 0.27295285 | D21: =D10/D12 -> 0.30136986 | E21: =E10/E12 -> 0.25462963 | F21: =F10/F12 -> 0.20609777 | G21: =G10/G12 -> 0.18003273 | H21: =H10/H12 -> 0.15224913 | I21: =I10/I12 -> 0.12304251
A22: Carry | C22: =C11/C12 -> 0.0078163772 | D22: =D11/D12 -> 0.010958904 | E22: =E11/E12 -> 0.015084877 | F22: =F11/F12 -> 0.019042753 | G22: =G11/G12 -> 0.020419755 | H22: =H11/H12 -> 0.021704939 | I22: =I11/I12 -> 0.023266219

Sheet P&L
A1: Profit & Loss
A2: 7-year projection ($mm).
A4: ($ in millions unless noted) | C4: 2026 | D4: 2027 | E4: 2028 | F4: 2029 | G4: 2030 | H4: 2031 | I4: 2032
A6: Revenue | C6: ='Revenue Build'!C12 -> 4.03 | D6: ='Revenue Build'!D12 -> 18.25 | E6: ='Revenue Build'!E12 -> 51.84 | F6: ='Revenue Build'!F12 -> 117.42 | G6: ='Revenue Build'!G12 -> 207.74 | H6: ='Revenue Build'!H12 -> 317.9 | I6: ='Revenue Build'!I12 -> 447
A7: Cost of revenue | C7: =-C6*Assumptions!C36 -> -1.9344 | D7: =-D6*Assumptions!D36 -> -7.665 | E7: =-E6*Assumptions!E36 -> -18.6624 | F7: =-F6*Assumptions!F36 -> -35.226 | G7: =-G6*Assumptions!G36 -> -54.0124 | H7: =-H6*Assumptions!H36 -> -76.296 | I7: =-I6*Assumptions!I36 -> -98.34
A8: Gross profit | C8: =C6+C7 -> 2.0956 | D8: =D6+D7 -> 10.585 | E8: =E6+E7 -> 33.1776 | F8: =F6+F7 -> 82.194 | G8: =G6+G7 -> 153.7276 | H8: =H6+H7 -> 241.604 | I8: =I6+I7 -> 348.66
A9: Gross margin % | C9: =C8/C6 -> 0.52 | D9: =D8/D6 -> 0.58 | E9: =E8/E6 -> 0.64 | F9: =F8/F6 -> 0.7 | G9: =G8/G6 -> 0.74 | H9: =H8/H6 -> 0.76 | I9: =I8/I6 -> 0.78
A11: Operating expenses
A12: Personnel | C12: =-Assumptions!C32*Assumptions!$C$33/1000 -> -5.775 | D12: =-Assumptions!D32*Assumptions!$C$33/1000 -> -14.85 | E12: =-Assumptions!E32*Assumptions!$C$33/1000 -> -29.7 | F12: =-Assumptions!F32*Assumptions!$C$33/1000 -> -52.8 | G12: =-Assumptions!G32*Assumptions!$C$33/1000 -> -75.9 | H12: =-Assumptions!H32*Assumptions!$C$33/1000 -> -92.4 | I12: =-Assumptions!I32*Assumptions!$C$33/1000 -> -107.25
A13: Marketing & programs | C13: =-Assumptions!C34 -> -3 | D13: =-Assumptions!D34 -> -10 | E13: =-Assumptions!E34 -> -22 | F13: =-Assumptions!F34 -> -38 | G13: =-Assumptions!G34 -> -52 | H13: =-Assumptions!H34 -> -62 | I13: =-Assumptions!I34 -> -70
A14: Other G&A | C14: =-Assumptions!C35 -> -2 | D14: =-Assumptions!D35 -> -5 | E14: =-Assumptions!E35 -> -10 | F14: =-Assumptions!F35 -> -18 | G14: =-Assumptions!G35 -> -26 | H14: =-Assumptions!H35 -> -34 | I14: =-Assumptions!I35 -> -40
A15: Total operating expenses | C15: =SUM(C12:C14) -> -10.775 | D15: =SUM(D12:D14) -> -29.85 | E15: =SUM(E12:E14) -> -61.7 | F15: =SUM(F12:F14) -> -108.8 | G15: =SUM(G12:G14) -> -153.9 | H15: =SUM(H12:H14) -> -188.4 | I15: =SUM(I12:I14) -> -217.25
A16: EBITDA | C16: =C8+C15 -> -8.6794 | D16: =D8+D15 -> -19.265 | E16: =E8+E15 -> -28.5224 | F16: =F8+F15 -> -26.606 | G16: =G8+G15 -> -0.1724 | H16: =H8+H15 -> 53.204 | I16: =I8+I15 -> 131.41
A17: EBITDA margin % | C17: =C16/C6 -> -2.1536973 | D17: =D16/D6 -> -1.0556164 | E17: =E16/E6 -> -0.55020062 | F17: =F16/F6 -> -0.22658832 | G17: =G16/G6 -> -0.00082988351 | H17: =H16/H6 -> 0.16736081 | I17: =I16/I6 -> 0.2939821
A19: Headcount (#) | C19: =Assumptions!C32 -> 35 | D19: =Assumptions!D32 -> 90 | E19: =Assumptions!E32 -> 180 | F19: =Assumptions!F32 -> 320 | G19: =Assumptions!G32 -> 460 | H19: =Assumptions!H32 -> 560 | I19: =Assumptions!I32 -> 650
A20: Revenue / employee ($000) | C20: =C6*1000/Assumptions!C32 -> 115.14286 | D20: =D6*1000/Assumptions!D32 -> 202.77778 | E20: =E6*1000/Assumptions!E32 -> 288 | F20: =F6*1000/Assumptions!F32 -> 366.9375 | G20: =G6*1000/Assumptions!G32 -> 451.6087 | H20: =H6*1000/Assumptions!H32 -> 567.67857 | I20: =I6*1000/Assumptions!I32 -> 687.69231

Sheet Market
A1: Market Opportunity — TAM / SAM / SOM
A2: Top-down sizing of the CarbonOS revenue opportunity (Year 7 / 2032 basis).
A4: Metric | B4: Value | C4: Basis / source
A5: Global primary issuance value ($mm, 2032) | B5: =Assumptions!I9 -> 41600 | C5: MSCI $7-35B by 2030; McKinsey >$50B
A6: Global secondary GMV ($mm, 2032) | B6: =Assumptions!I11 -> 124800 | C6: ~3x turnover (4-5 transfers typical)
A7: Capital arranged across market ($mm, 2032) | B7: =Assumptions!I21/0.05 -> 32000 | C7: platform capital / penetration
A9: TAM — platform revenue pool at 100% adoption | B9: ='P&L'!I6/Assumptions!I14 -> 8940 | C9: Year-7 revenue / Year-7 penetration
A10: SAM — serviceable (developed VCM + Article 6) | B10: =B9*0.6 -> 5364 | C10: ~60% of TAM serviceable near-term
A11: SOM — CarbonOS target at 5% penetration | B11: ='P&L'!I6 -> 447 | C11: modeled Year-7 revenue

Sheet Unit Economics
A1: Unit Economics — Developer SaaS
A2: Illustrative SaaS metrics for the developer subscription line.
A4: Metric | B4: Value | C4: Note
A5: ARPU per project ($/yr) | B5: =Assumptions!C24 -> 45000 | C5: blended tiers
A6: Gross margin (steady state) | B6: 0.78 | C6: software-heavy
A7: Annual gross profit per project ($) | B7: =B5*B6 -> 35100 | C7: ARPU x GM
A8: Gross logo churn (annual) | B8: 0.12 | C8: sticky workflow system of record
A9: Avg customer lifetime (yrs) | B9: =1/B8 -> 8.3333333 | C9: 1 / churn
A10: Lifetime value — LTV ($) | B10: =B7*B9 -> 292500 | C10: GP x lifetime
A11: Customer acquisition cost — CAC ($) | B11: 28000 | C11: enterprise-assisted sales
A12: LTV / CAC (x) | B12: =B10/B11 -> 10.446429 | C12: target > 3.0x
A13: CAC payback (months) | B13: =B11/(B7/12) -> 9.5726496 | C13: months of gross profit
A14: Net revenue retention | B14: 1.2 | C14: expansion across engines

Sheet Valuation
A1: Valuation — Comparable Multiples
A2: Enterprise value implied by vertical-SaaS + fintech comps applied to Year-7 revenue.
A4: Comparable | B4: EV/Revenue | C4: Reference
A5: Carta | B5: 14.8 | C5: $7.4B EV / $0.5B ARR
A6: Procore | B6: 6.5 | C6: ~$7B EV / ~$1.1B rev
A7: Construction-tech median | B7: 7.5 | C7: vertical SaaS 2026
A8: Vertical SaaS + embedded fintech premium | B8: 1.45 | C8: 33-60% premium (mid 45%)
A10: Year-7 revenue ($mm) | B10: ='P&L'!I6 -> 447
A11: Year-7 EBITDA ($mm) | B11: ='P&L'!I16 -> 131.41
A13: Implied Enterprise Value | B13: Low | C13: Mid | D13: High
A14: EV/Revenue multiple | B14: 6 | C14: 9 | D14: 12
A15: Enterprise value ($mm) | B15: =B14*B10 -> 2682 | C15: =C14*B10 -> 4023 | D15: =D14*B10 -> 5364
A17: Note: software/algorithm IP + data moat + embedded fintech support the upper range.

Sheet Scenarios
A1: Scenarios — Penetration Sensitivity (Year 7)
A2: Revenue and EV scale with platform penetration of global throughput.
A4: Scenario | B4: Bear | C4: Base | D4: Bull
A5: Penetration of throughput | B5: 0.025 | C5: 0.05 | D5: 0.08
A6: Year-7 revenue ($mm) | B6: ='P&L'!I6*B5/Assumptions!I14 -> 223.5 | C6: ='P&L'!I6*C5/Assumptions!I14 -> 447 | D6: ='P&L'!I6*D5/Assumptions!I14 -> 715.2
A7: EV at 9.0x revenue ($mm) | B7: =B6*9 -> 2011.5 | C7: =C6*9 -> 4023 | D7: =D6*9 -> 6436.8

Sheet Sources
A1: Sources & Benchmarks
A2: Topic | B2: Reference
A3: Voluntary carbon market size & forecasts | B3: MSCI ($7-35B by 2030); McKinsey (>$50B by 2030); BloombergNEF ($146/t removal 2030, $238/t 2050)
A4: Compliance carbon pricing revenue | B4: World Bank, State & Trends of Carbon Pricing 2024 — >$104B (2023)
A5: Retirements / issuance volumes | B5: Sylvera Q2-2025 snapshot — ~176M retired 2024; ~77M issued Q2-2025; Verra ~63% share
A6: Registry economics | B6: Verra Program Fee Schedule 2024 — $0.23/VCU issuance levy; $0.02 transfer/retirement; $2,500 registration review
A7: MRV cost share | B7: Industry: MRV ~20-30% of credit revenue; ~2-3 yrs to first issuance
A8: Comparable platforms | B8: Carta ($500M ARR/$7.4B); Procore (~$1.1B rev/~$7B EV); ServiceTitan payments 1.17% take
A9: Vertical SaaS premium | B9: Embedded-fintech vertical SaaS commands 33-60% valuation premium
A11: Figures are illustrative model outputs, not a forecast of actual results or financial advice.
